thepasswordgenerator/__init__.py
thepasswordgenerator/password_generator.py
thepasswordgenerator-1.2.1.dist-info/LICENSE.txt
thepasswordgenerator-1.2.1.dist-info/METADATA
thepasswordgenerator-1.2.1.dist-info/WHEEL
thepasswordgenerator-1.2.1.dist-info/top_level.txt
thepasswordgenerator-1.2.1.dist-info/RECORD
