Metadata-Version: 2.1
Name: thepasswordgenerator
Version: 1.2.1
Summary: Generate passwords within your scripts or programs in one line!
Home-page: https://github.com/agent47nh/the-password-generator
Author: Naimul Hasan
Author-email: agent47nh9@gmail.com
License: AGPLv3
Project-URL: Documentation, https://github.com/agent47nh/the-password-generator/blob/main/README.md
Project-URL: Source, https://github.com/agent47nh/the-password-generator
Project-URL: Tracker, https://github.com/agent47nh/the-password-generator/issues
Keywords: passwords generator password-generator
Platform: UNKNOWN
Classifier: Development Status :: 4 - Beta
Classifier: Intended Audience :: Developers
Classifier: Programming Language :: Python :: 3.9
Requires-Python: >=3
License-File: LICENSE.txt
